ftmocds/__init__.py
ftmocds/cli.py
ftmocds/convert.py
followthemoney_ocds-0.3.0.dist-info/LICENSE
followthemoney_ocds-0.3.0.dist-info/METADATA
followthemoney_ocds-0.3.0.dist-info/WHEEL
followthemoney_ocds-0.3.0.dist-info/entry_points.txt
followthemoney_ocds-0.3.0.dist-info/namespace_packages.txt
followthemoney_ocds-0.3.0.dist-info/top_level.txt
followthemoney_ocds-0.3.0.dist-info/RECORD
