Metadata-Version: 2.1
Name: followthemoney-ocds
Version: 0.3.0
Author: Organized Crime and Corruption Reporting Project
Author-email: data@occrp.org
License: MIT
License-File: LICENSE
Requires-Dist: followthemoney >=1.29.5
